<?xml version="1.0" encoding="utf-8"?>
<!DOCTYPE hibernate-mapping PUBLIC "-//Hibernate/Hibernate Mapping DTD 3.0//EN"
"http://hibernate.sourceforge.net/hibernate-mapping-3.0.dtd">
<!-- 
    Mapping file autogenerated by MyEclipse Persistence Tools
-->
<hibernate-mapping>
    <class name="cn.aichange.bean.Dept" table="dept" catalog="crm_sys">
        <id name="id" type="java.lang.Integer">
            <column name="id" />
            <generator class="native" />
        </id>
        <property name="deptName" type="java.lang.String">
            <column name="deptName" length="20" />
        </property>
        <property name="remarks" type="java.lang.String">
            <column name="remarks" length="20" />
        </property>
        <set name="employees" inverse="true">
            <key>
                <column name="dept_id" />
            </key>
            <one-to-many class="cn.aichange.bean.Employee" />
        </set>
    </class>
</hibernate-mapping>
